youtube_qa/__init__.py
youtube_qa/converters.py
youtube_qa/models.py
youtube_qa/sentence_transformer.py
youtube_qa/youtube_video_index.py
youtube_qa-1.0.4.dist-info/METADATA
youtube_qa-1.0.4.dist-info/WHEEL
youtube_qa-1.0.4.dist-info/RECORD
