Metadata-Version: 2.1
Name: youtube-qa
Version: 1.0.4
Summary: Question answering over YouTube videos with embeddings and LLMs.
Home-page: https://github.com/jakecyr/youtube-qa
License: MIT
Author: Jake Cyr
Author-email: cyrjake@gmail.com
Requires-Python: >=3.9,<3.13
Classifier: License :: OSI Approved :: MIT License
Classifier: Programming Language :: Python :: 3
Classifier: Programming Language :: Python :: 3.9
Classifier: Programming Language :: Python :: 3.10
Classifier: Programming Language :: Python :: 3.11
Classifier: Programming Language :: Python :: 3.12
Requires-Dist: llama-index (>=0.10.56,<0.11.0)
Requires-Dist: sentence-transformers (>=2.5.1,<3.0.0)
Requires-Dist: youtube-search (>=2.1.2,<3.0.0)
Requires-Dist: youtube-transcript-api (>=0.6.2,<0.7.0)
Project-URL: Repository, https://github.com/jakecyr/youtube-qa
